dynamo_api/__init__.py
dynamo_api-0.1.1.dist-info/WHEEL
dynamo_api-0.1.1.dist-info/METADATA
dynamo_api-0.1.1.dist-info/RECORD
